LICENSE
README
pyproject.toml
setup.py
PyMalware/__init__.py
PyMalware/cpu.py
PyMalware/keylogger.py
PyMalware/ransomware.py
PyMalware/wifi.py
PyMalware/win32.py
PyMalware.egg-info/PKG-INFO
PyMalware.egg-info/SOURCES.txt
PyMalware.egg-info/dependency_links.txt
PyMalware.egg-info/requires.txt
PyMalware.egg-info/top_level.txt