Metadata-Version: 2.1
Name: PyMalware
Version: 1.0
Summary: A python package to make malware creation easier
Home-page: https://github.com/PthePro777YT/PyMalware
Download-URL: https://github.com/PthePro777YT/PyMalware/releases/download/v_01/PyMalware.tar.gz
Author: PthePro777 YT
Author-email: PthePro777 YT <pthepro777ytb@gmail.com>
License: MIT
Keywords: Malware,Advanced,Python,Dev
Classifier: Development Status :: 3 - Alpha
Classifier: Intended Audience :: Developers
Classifier: Topic :: Software Development :: Build Tools
Classifier: License :: OSI Approved :: MIT License
Classifier: Programming Language :: Python :: 3
Classifier: Programming Language :: Python :: 3.4
Classifier: Programming Language :: Python :: 3.5
Classifier: Programming Language :: Python :: 3.6
Classifier: Programming Language :: Python :: 3.11
Requires-Python: >=3.7
License-File: LICENSE
